http_testing/__init__.py
http_testing/_record.py
http_testing/assertions.py
http_testing/cookie.py
http_testing/page_checker.py
http_testing/plugin.py
http_testing/py.typed
http_testing/validators.py
http_testing/_assertion_elements/__init__.py
http_testing/_assertion_elements/assert_element_checker_base.py
http_testing/_assertion_elements/assertion_data.py
http_testing/_assertion_elements/content_assertion.py
http_testing/_assertion_elements/cookies_assertion.py
http_testing/_assertion_elements/headers_assertion.py
http_testing/_assertion_elements/status_code_assertion.py
pytest_httptesting-0.10.0.dist-info/LICENSE
pytest_httptesting-0.10.0.dist-info/METADATA
pytest_httptesting-0.10.0.dist-info/WHEEL
pytest_httptesting-0.10.0.dist-info/entry_points.txt
pytest_httptesting-0.10.0.dist-info/top_level.txt
pytest_httptesting-0.10.0.dist-info/RECORD
