Metadata-Version: 2.1
Name: pytest-httptesting
Version: 0.10.0
Summary: http_testing framework on top of pytest
Author-email: heqile <mr.qile@gmail.com>, HE Qile <mr.qile@gmail.com>
License: MIT
Project-URL: homepage, https://github.com/heqile/http_testing
Project-URL: repository, https://github.com/heqile/http_testing
Requires-Python: >=3.8
License-File: LICENSE
Requires-Dist: pytest>=8.2.0
Requires-Dist: httpx>=0.28.0
Requires-Dist: attrs>=24.2.0
